LordUtils/__init__.py
LordUtils/console.py
LordUtils/env.py
LordUtils/json_encoder.py
LordUtils/customs/__init__.py
LordUtils/data/__init__.py
LordUtils/data/datasets/lang.json
LordUtils/decorators/__init__.py
LordUtils/regs/__init__.py
LordUtils/regs/patterns.py
LordUtils/sorting/__init__.py
LordUtils/utils/__init__.py
LordUtils-2023.3.26.dist-info/METADATA
LordUtils-2023.3.26.dist-info/WHEEL
LordUtils-2023.3.26.dist-info/top_level.txt
LordUtils-2023.3.26.dist-info/RECORD
