Metadata-Version: 2.1
Name: LordUtils
Version: 2023.3.26
Summary: Helper Package for other Lord packages
Author-email: lordbex <lordibex@protonmail.com>
Maintainer-email: lordbex <lordibex@protonmail.com>
Project-URL: homepage, https://github.com/BexWorld/LordUtils.git
Project-URL: repository, https://github.com/BexWorld/LordUtils.git
Requires-Python: >=3.10
Requires-Dist: regex
Requires-Dist: validators
Requires-Dist: rich
